setup.py
pydouban/__init__.py
pydouban/client.py
pydouban/exceptions.py
pydouban/http.py
pydouban/t.py
pydouban.egg-info/PKG-INFO
pydouban.egg-info/SOURCES.txt
pydouban.egg-info/dependency_links.txt
pydouban.egg-info/requires.txt
pydouban.egg-info/top_level.txt