Metadata-Version: 1.0
Name: pydouban
Version: 0.1.1
Summary: A simple python libary for douban.com that contains some basic functions
Home-page: http://github.com/tianyu0915/pydouban
Author: TY
Author-email: tianyu0915@gmail.com
License: UNKNOWN
Keywords: douban,libary
Platform: UNKNOWN
